README.md
setup.py
BiImageTransform/BiImageTransform.py
BiImageTransform/__init__.py
BiImageTransform/functional.py
BiImageTransform.egg-info/PKG-INFO
BiImageTransform.egg-info/SOURCES.txt
BiImageTransform.egg-info/dependency_links.txt
BiImageTransform.egg-info/requires.txt
BiImageTransform.egg-info/top_level.txt